pyfixest-0.40.1.dist-info/METADATA
pyfixest-0.40.1.dist-info/WHEEL
pyfixest-0.40.1.dist-info/licenses/LICENSE.md
pyfixest.libs/libgcc_s-27e5a392.so.1
pyfixest/__init__.py
pyfixest/core/__init__.py
pyfixest/core/_core_impl.cpython-313t-i386-linux-musl.so
pyfixest/core/_core_impl.pyi
pyfixest/core/collinear.py
pyfixest/core/crv1.py
pyfixest/core/demean.py
pyfixest/core/nested_fixed_effects.py
pyfixest/core/py.typed
pyfixest/did/__init__.py
pyfixest/did/data/df_het.csv
pyfixest/did/data/lpdidtestdata1.dta
pyfixest/did/did.py
pyfixest/did/did2s.py
pyfixest/did/estimation.py
pyfixest/did/lpdid.py
pyfixest/did/saturated_twfe.py
pyfixest/did/twfe.py
pyfixest/did/visualize.py
pyfixest/errors/__init__.py
pyfixest/estimation/FixestMulti_.py
pyfixest/estimation/FormulaParser.py
pyfixest/estimation/__init__.py
pyfixest/estimation/backends.py
pyfixest/estimation/ccv.py
pyfixest/estimation/cupy/__init__.py
pyfixest/estimation/cupy/demean_cupy_.py
pyfixest/estimation/decomposition.py
pyfixest/estimation/demean_.py
pyfixest/estimation/demean_jax_.py
pyfixest/estimation/detect_singletons_.py
pyfixest/estimation/detect_singletons_jax.py
pyfixest/estimation/estimation.py
pyfixest/estimation/fegaussian_.py
pyfixest/estimation/feglm_.py
pyfixest/estimation/feiv_.py
pyfixest/estimation/felogit_.py
pyfixest/estimation/feols_.py
pyfixest/estimation/feols_compressed_.py
pyfixest/estimation/fepois_.py
pyfixest/estimation/feprobit_.py
pyfixest/estimation/jax/demean_jax_.py
pyfixest/estimation/jax/detect_singletons_jax.py
pyfixest/estimation/literals.py
pyfixest/estimation/model_matrix_fixest_.py
pyfixest/estimation/multcomp.py
pyfixest/estimation/numba/find_collinear_variables_nb.py
pyfixest/estimation/numba/nested_fixef_nb.py
pyfixest/estimation/prediction.py
pyfixest/estimation/quantreg/QuantregMulti.py
pyfixest/estimation/quantreg/__init__.py
pyfixest/estimation/quantreg/frisch_newton_ip.py
pyfixest/estimation/quantreg/quantreg_.py
pyfixest/estimation/quantreg/utils.py
pyfixest/estimation/ritest.py
pyfixest/estimation/solvers.py
pyfixest/estimation/vcov_utils.py
pyfixest/report/__init__.py
pyfixest-0.40.1.dist-info/RECORD
