Metadata-Version: 2.4
Name: pyfixest
Version: 0.40.1
Requires-Dist: scipy>=1.6,<1.16
Requires-Dist: formulaic>=1.1.0
Requires-Dist: pandas>=1.1.0
Requires-Dist: numba>=0.58.0
Requires-Dist: seaborn>=0.13.2
Requires-Dist: tabulate>=0.9.0
Requires-Dist: tqdm>=4.0.0
Requires-Dist: great-tables>=0.10.0
Requires-Dist: numpy>=1.25.2
Requires-Dist: narwhals>=1.13.3
Requires-Dist: joblib>=1.4.2,<2
Requires-Dist: jax>=0.4.15 ; extra == 'jax'
Requires-Dist: jaxlib>=0.4.15 ; extra == 'jax'
Requires-Dist: lets-plot>=4.0.0 ; extra == 'plots'
Provides-Extra: jax
Provides-Extra: plots
License-File: LICENSE.md
Summary: Fast high dimensional fixed effect estimation following syntax of the fixest R package.
Author: Styfen Schär
Author-email: Alexander Fischer <alexander-fischer1801@t-online.de>
License: MIT
Requires-Python: >=3.9
